demo_PySide6_GlobalHotkeys/__init__.py
demo_PySide6_GlobalHotkeys/main.py
demo_pyside6_globalhotkeys-0.0.2.dist-info/licenses/LICENSE
demo_pyside6_globalhotkeys-0.0.2.dist-info/METADATA
demo_pyside6_globalhotkeys-0.0.2.dist-info/WHEEL
demo_pyside6_globalhotkeys-0.0.2.dist-info/entry_points.txt
demo_pyside6_globalhotkeys-0.0.2.dist-info/top_level.txt
demo_pyside6_globalhotkeys-0.0.2.dist-info/RECORD
