Metadata-Version: 2.4
Name: demo-PySide6-GlobalHotkeys
Version: 0.0.2
Summary: Demo app for system-wide hotkeys for applications developed with PySide6.
Author-email: develOseven <devel.oseven@gmail.com>
License-Expression: MIT
Project-URL: Homepage, https://github.com/develOseven/demo-PySide6-GlobalHotkeys
Project-URL: Issues, https://github.com/develOseven/demo-PySide6-GlobalHotkeys/issues
Classifier: Programming Language :: Python :: 3
Classifier: Operating System :: OS Independent
Requires-Python: >=3.10.8
License-File: LICENSE
Requires-Dist: PySide6-GlobalHotkeys
Dynamic: license-file
